django_fsm_dynamic/__init__.py
django_fsm_dynamic/__version__.py
django_fsm_dynamic/core.py
django_fsm_dynamic-1.1.0.dist-info/licenses/LICENSE
django_fsm_dynamic-1.1.0.dist-info/METADATA
django_fsm_dynamic-1.1.0.dist-info/WHEEL
django_fsm_dynamic-1.1.0.dist-info/top_level.txt
django_fsm_dynamic-1.1.0.dist-info/RECORD
