Metadata-Version: 2.4
Name: django-fsm-dynamic
Version: 1.1.0
Summary: Dynamic workflow extensions for django-fsm-2
Author-email: LevIT <info@levit.be>
License: MIT
Project-URL: Homepage, https://gitlab.levitnet.be/levit/django-fsm-dynamic
Project-URL: Repository, https://gitlab.levitnet.be/levit/django-fsm-dynamic.git
Keywords: django,fsm,workflow,state-machine,dynamic
Classifier: Development Status :: 4 - Beta
Classifier: Framework :: Django
Classifier: Framework :: Django :: 5.0
Classifier: Framework :: Django :: 5.1
Classifier: Framework :: Django :: 5.2
Classifier: Intended Audience :: Developers
Classifier: Programming Language :: Python :: 3.10
Classifier: Programming Language :: Python :: 3.11
Classifier: Programming Language :: Python :: 3.12
Classifier: Programming Language :: Python :: 3.13
Requires-Python: >=3.10
License-File: LICENSE
Requires-Dist: django>=5.0
Requires-Dist: django-fsm-2>=4.0.0
Provides-Extra: dev
Requires-Dist: build>=1.2.2.post1; extra == "dev"
Requires-Dist: coverage; extra == "dev"
Requires-Dist: nox; extra == "dev"
Requires-Dist: ruff; extra == "dev"
Requires-Dist: setuptools>=75.3.2; extra == "dev"
Requires-Dist: twine>=6.1.0; extra == "dev"
Dynamic: license-file
